pybeam/__init__.py
pybeam/analyze.py
pybeam/loading_case.py
pybeam/loads.py
pybeam/materials.py
pybeam/members.py
pybeam/profiles.py
pybeam/py.typed
pybeam/visualizers.py
pybeam_structural-0.1.0a0.dist-info/licenses/LICENSE
pybeam_structural-0.1.0a0.dist-info/METADATA
pybeam_structural-0.1.0a0.dist-info/WHEEL
pybeam_structural-0.1.0a0.dist-info/top_level.txt
pybeam_structural-0.1.0a0.dist-info/RECORD
