Metadata-Version: 2.4
Name: pybeam-structural
Version: 0.1.0a0
Summary: A simple beam analysis tool
Author: Damian Games
License: MIT License
Project-URL: Homepage, https://github.com/DGames95/pybeam
Project-URL: Bug Tracker, https://github.com/DGames95/pybeam/issues
Requires-Python: >=3.8
License-File: LICENSE
Requires-Dist: numpy>=1.22
Requires-Dist: matplotlib>=3.0
Provides-Extra: dev
Requires-Dist: pytest>=7.0; extra == "dev"
Requires-Dist: mypy; extra == "dev"
Requires-Dist: pip-tools; extra == "dev"
Requires-Dist: coverage; extra == "dev"
Requires-Dist: pylint; extra == "dev"
Requires-Dist: sphinx; extra == "dev"
Requires-Dist: sphinx-rtd-theme; extra == "dev"
Requires-Dist: sphinx-autodoc-typehints; extra == "dev"
Requires-Dist: toml; extra == "dev"
Dynamic: license-file
